<annotation>
	<folder></folder>
	<filename>000381_jpg.rf.83bd7104a4fd0bb5a0532f9c6710f7ce.jpg</filename>
	<path>000381_jpg.rf.83bd7104a4fd0bb5a0532f9c6710f7ce.jpg</path>
	<source>
		<database>roboflow.ai</database>
	</source>
	<size>
		<width>416</width>
		<height>416</height>
		<depth>3</depth>
	</size>
	<segmented>0</segmented>
	<object>
		<name>helmet</name>
		<pose>Unspecified</pose>
		<truncated>0</truncated>
		<difficult>0</difficult>
		<occluded>0</occluded>
		<bndbox>
			<xmin>156</xmin>
			<xmax>220</xmax>
			<ymin>114</ymin>
			<ymax>197</ymax>
		</bndbox>
	</object>
	<object>
		<name>helmet</name>
		<pose>Unspecified</pose>
		<truncated>0</truncated>
		<difficult>0</difficult>
		<occluded>0</occluded>
		<bndbox>
			<xmin>1</xmin>
			<xmax>54</xmax>
			<ymin>102</ymin>
			<ymax>172</ymax>
		</bndbox>
	</object>
	<object>
		<name>helmet</name>
		<pose>Unspecified</pose>
		<truncated>0</truncated>
		<difficult>0</difficult>
		<occluded>0</occluded>
		<bndbox>
			<xmin>156</xmin>
			<xmax>221</xmax>
			<ymin>0</ymin>
			<ymax>25</ymax>
		</bndbox>
	</object>
	<object>
		<name>helmet</name>
		<pose>Unspecified</pose>
		<truncated>0</truncated>
		<difficult>0</difficult>
		<occluded>0</occluded>
		<bndbox>
			<xmin>0</xmin>
			<xmax>54</xmax>
			<ymin>0</ymin>
			<ymax>37</ymax>
		</bndbox>
	</object>
</annotation>
