<annotation>
	<folder></folder>
	<filename>000654_jpg.rf.8b74b3d1b15e6bbb3c86c639aa10508c.jpg</filename>
	<path>000654_jpg.rf.8b74b3d1b15e6bbb3c86c639aa10508c.jpg</path>
	<source>
		<database>roboflow.ai</database>
	</source>
	<size>
		<width>416</width>
		<height>416</height>
		<depth>3</depth>
	</size>
	<segmented>0</segmented>
	<object>
		<name>helmet</name>
		<pose>Unspecified</pose>
		<truncated>0</truncated>
		<difficult>0</difficult>
		<occluded>0</occluded>
		<bndbox>
			<xmin>169</xmin>
			<xmax>199</xmax>
			<ymin>245</ymin>
			<ymax>281</ymax>
		</bndbox>
	</object>
	<object>
		<name>helmet</name>
		<pose>Unspecified</pose>
		<truncated>0</truncated>
		<difficult>0</difficult>
		<occluded>0</occluded>
		<bndbox>
			<xmin>336</xmin>
			<xmax>359</xmax>
			<ymin>232</ymin>
			<ymax>261</ymax>
		</bndbox>
	</object>
	<object>
		<name>helmet</name>
		<pose>Unspecified</pose>
		<truncated>0</truncated>
		<difficult>0</difficult>
		<occluded>0</occluded>
		<bndbox>
			<xmin>103</xmin>
			<xmax>121</xmax>
			<ymin>94</ymin>
			<ymax>115</ymax>
		</bndbox>
	</object>
	<object>
		<name>helmet</name>
		<pose>Unspecified</pose>
		<truncated>0</truncated>
		<difficult>0</difficult>
		<occluded>0</occluded>
		<bndbox>
			<xmin>128</xmin>
			<xmax>153</xmax>
			<ymin>187</ymin>
			<ymax>205</ymax>
		</bndbox>
	</object>
	<object>
		<name>helmet</name>
		<pose>Unspecified</pose>
		<truncated>0</truncated>
		<difficult>0</difficult>
		<occluded>0</occluded>
		<bndbox>
			<xmin>125</xmin>
			<xmax>143</xmax>
			<ymin>264</ymin>
			<ymax>287</ymax>
		</bndbox>
	</object>
	<object>
		<name>helmet</name>
		<pose>Unspecified</pose>
		<truncated>0</truncated>
		<difficult>0</difficult>
		<occluded>0</occluded>
		<bndbox>
			<xmin>208</xmin>
			<xmax>226</xmax>
			<ymin>227</ymin>
			<ymax>247</ymax>
		</bndbox>
	</object>
	<object>
		<name>helmet</name>
		<pose>Unspecified</pose>
		<truncated>0</truncated>
		<difficult>0</difficult>
		<occluded>0</occluded>
		<bndbox>
			<xmin>312</xmin>
			<xmax>335</xmax>
			<ymin>238</ymin>
			<ymax>264</ymax>
		</bndbox>
	</object>
	<object>
		<name>helmet</name>
		<pose>Unspecified</pose>
		<truncated>0</truncated>
		<difficult>0</difficult>
		<occluded>0</occluded>
		<bndbox>
			<xmin>368</xmin>
			<xmax>382</xmax>
			<ymin>251</ymin>
			<ymax>270</ymax>
		</bndbox>
	</object>
	<object>
		<name>helmet</name>
		<pose>Unspecified</pose>
		<truncated>0</truncated>
		<difficult>0</difficult>
		<occluded>0</occluded>
		<bndbox>
			<xmin>103</xmin>
			<xmax>122</xmax>
			<ymin>0</ymin>
			<ymax>11</ymax>
		</bndbox>
	</object>
</annotation>
