<annotation>
	<folder></folder>
	<filename>001130_jpg.rf.afd46c8efa2dbe0e6a760558681f5dd4.jpg</filename>
	<path>001130_jpg.rf.afd46c8efa2dbe0e6a760558681f5dd4.jpg</path>
	<source>
		<database>roboflow.ai</database>
	</source>
	<size>
		<width>416</width>
		<height>416</height>
		<depth>3</depth>
	</size>
	<segmented>0</segmented>
	<object>
		<name>helmet</name>
		<pose>Unspecified</pose>
		<truncated>0</truncated>
		<difficult>0</difficult>
		<occluded>0</occluded>
		<bndbox>
			<xmin>55</xmin>
			<xmax>138</xmax>
			<ymin>118</ymin>
			<ymax>213</ymax>
		</bndbox>
	</object>
	<object>
		<name>helmet</name>
		<pose>Unspecified</pose>
		<truncated>0</truncated>
		<difficult>0</difficult>
		<occluded>0</occluded>
		<bndbox>
			<xmin>54</xmin>
			<xmax>138</xmax>
			<ymin>0</ymin>
			<ymax>21</ymax>
		</bndbox>
	</object>
</annotation>
