<annotation>
	<folder></folder>
	<filename>002763_jpg.rf.fb48fc3bd8b6202926932a011dea8590.jpg</filename>
	<path>002763_jpg.rf.fb48fc3bd8b6202926932a011dea8590.jpg</path>
	<source>
		<database>roboflow.ai</database>
	</source>
	<size>
		<width>416</width>
		<height>416</height>
		<depth>3</depth>
	</size>
	<segmented>0</segmented>
	<object>
		<name>helmet</name>
		<pose>Unspecified</pose>
		<truncated>0</truncated>
		<difficult>0</difficult>
		<occluded>0</occluded>
		<bndbox>
			<xmin>195</xmin>
			<xmax>250</xmax>
			<ymin>108</ymin>
			<ymax>170</ymax>
		</bndbox>
	</object>
	<object>
		<name>helmet</name>
		<pose>Unspecified</pose>
		<truncated>0</truncated>
		<difficult>0</difficult>
		<occluded>0</occluded>
		<bndbox>
			<xmin>247</xmin>
			<xmax>301</xmax>
			<ymin>125</ymin>
			<ymax>194</ymax>
		</bndbox>
	</object>
</annotation>
