<annotation>
	<folder></folder>
	<filename>000779_jpg.rf.be3a90613a9c158bbe2aac1e2959901a.jpg</filename>
	<path>000779_jpg.rf.be3a90613a9c158bbe2aac1e2959901a.jpg</path>
	<source>
		<database>roboflow.ai</database>
	</source>
	<size>
		<width>416</width>
		<height>416</height>
		<depth>3</depth>
	</size>
	<segmented>0</segmented>
	<object>
		<name>helmet</name>
		<pose>Unspecified</pose>
		<truncated>0</truncated>
		<difficult>0</difficult>
		<occluded>0</occluded>
		<bndbox>
			<xmin>149</xmin>
			<xmax>177</xmax>
			<ymin>135</ymin>
			<ymax>167</ymax>
		</bndbox>
	</object>
	<object>
		<name>helmet</name>
		<pose>Unspecified</pose>
		<truncated>0</truncated>
		<difficult>0</difficult>
		<occluded>0</occluded>
		<bndbox>
			<xmin>212</xmin>
			<xmax>236</xmax>
			<ymin>111</ymin>
			<ymax>145</ymax>
		</bndbox>
	</object>
	<object>
		<name>helmet</name>
		<pose>Unspecified</pose>
		<truncated>0</truncated>
		<difficult>0</difficult>
		<occluded>0</occluded>
		<bndbox>
			<xmin>149</xmin>
			<xmax>178</xmax>
			<ymin>0</ymin>
			<ymax>10</ymax>
		</bndbox>
	</object>
	<object>
		<name>helmet</name>
		<pose>Unspecified</pose>
		<truncated>0</truncated>
		<difficult>0</difficult>
		<occluded>0</occluded>
		<bndbox>
			<xmin>212</xmin>
			<xmax>237</xmax>
			<ymin>0</ymin>
			<ymax>34</ymax>
		</bndbox>
	</object>
</annotation>
