<annotation>
	<folder></folder>
	<filename>001186_jpg.rf.c81a51f4cfe2a6be2a80a2f1281429d8.jpg</filename>
	<path>001186_jpg.rf.c81a51f4cfe2a6be2a80a2f1281429d8.jpg</path>
	<source>
		<database>roboflow.ai</database>
	</source>
	<size>
		<width>416</width>
		<height>416</height>
		<depth>3</depth>
	</size>
	<segmented>0</segmented>
	<object>
		<name>helmet</name>
		<pose>Unspecified</pose>
		<truncated>0</truncated>
		<difficult>0</difficult>
		<occluded>0</occluded>
		<bndbox>
			<xmin>115</xmin>
			<xmax>175</xmax>
			<ymin>109</ymin>
			<ymax>177</ymax>
		</bndbox>
	</object>
	<object>
		<name>helmet</name>
		<pose>Unspecified</pose>
		<truncated>0</truncated>
		<difficult>0</difficult>
		<occluded>0</occluded>
		<bndbox>
			<xmin>238</xmin>
			<xmax>286</xmax>
			<ymin>72</ymin>
			<ymax>132</ymax>
		</bndbox>
	</object>
	<object>
		<name>helmet</name>
		<pose>Unspecified</pose>
		<truncated>0</truncated>
		<difficult>0</difficult>
		<occluded>0</occluded>
		<bndbox>
			<xmin>204</xmin>
			<xmax>229</xmax>
			<ymin>137</ymin>
			<ymax>165</ymax>
		</bndbox>
	</object>
	<object>
		<name>helmet</name>
		<pose>Unspecified</pose>
		<truncated>0</truncated>
		<difficult>0</difficult>
		<occluded>0</occluded>
		<bndbox>
			<xmin>115</xmin>
			<xmax>176</xmax>
			<ymin>0</ymin>
			<ymax>30</ymax>
		</bndbox>
	</object>
	<object>
		<name>helmet</name>
		<pose>Unspecified</pose>
		<truncated>0</truncated>
		<difficult>0</difficult>
		<occluded>0</occluded>
		<bndbox>
			<xmin>238</xmin>
			<xmax>286</xmax>
			<ymin>6</ymin>
			<ymax>66</ymax>
		</bndbox>
	</object>
</annotation>
