<annotation>
	<folder></folder>
	<filename>002507_jpg.rf.3e961a230ab0fc97513b289f75275f2d.jpg</filename>
	<path>002507_jpg.rf.3e961a230ab0fc97513b289f75275f2d.jpg</path>
	<source>
		<database>roboflow.ai</database>
	</source>
	<size>
		<width>416</width>
		<height>416</height>
		<depth>3</depth>
	</size>
	<segmented>0</segmented>
	<object>
		<name>helmet</name>
		<pose>Unspecified</pose>
		<truncated>0</truncated>
		<difficult>0</difficult>
		<occluded>0</occluded>
		<bndbox>
			<xmin>157</xmin>
			<xmax>237</xmax>
			<ymin>70</ymin>
			<ymax>178</ymax>
		</bndbox>
	</object>
	<object>
		<name>helmet</name>
		<pose>Unspecified</pose>
		<truncated>0</truncated>
		<difficult>0</difficult>
		<occluded>0</occluded>
		<bndbox>
			<xmin>157</xmin>
			<xmax>238</xmax>
			<ymin>0</ymin>
			<ymax>69</ymax>
		</bndbox>
	</object>
</annotation>
