<annotation>
	<folder></folder>
	<filename>003087_jpg.rf.45f6cae7f3c1c605a750e452d7353fa7.jpg</filename>
	<path>003087_jpg.rf.45f6cae7f3c1c605a750e452d7353fa7.jpg</path>
	<source>
		<database>roboflow.ai</database>
	</source>
	<size>
		<width>416</width>
		<height>416</height>
		<depth>3</depth>
	</size>
	<segmented>0</segmented>
	<object>
		<name>helmet</name>
		<pose>Unspecified</pose>
		<truncated>0</truncated>
		<difficult>0</difficult>
		<occluded>0</occluded>
		<bndbox>
			<xmin>79</xmin>
			<xmax>103</xmax>
			<ymin>142</ymin>
			<ymax>170</ymax>
		</bndbox>
	</object>
	<object>
		<name>helmet</name>
		<pose>Unspecified</pose>
		<truncated>0</truncated>
		<difficult>0</difficult>
		<occluded>0</occluded>
		<bndbox>
			<xmin>205</xmin>
			<xmax>233</xmax>
			<ymin>97</ymin>
			<ymax>120</ymax>
		</bndbox>
	</object>
	<object>
		<name>helmet</name>
		<pose>Unspecified</pose>
		<truncated>0</truncated>
		<difficult>0</difficult>
		<occluded>0</occluded>
		<bndbox>
			<xmin>205</xmin>
			<xmax>233</xmax>
			<ymin>23</ymin>
			<ymax>46</ymax>
		</bndbox>
	</object>
</annotation>
