<annotation>
	<folder></folder>
	<filename>003624_jpg.rf.00e3a029ad0e4e9ad6b792dd4f787dfd.jpg</filename>
	<path>003624_jpg.rf.00e3a029ad0e4e9ad6b792dd4f787dfd.jpg</path>
	<source>
		<database>roboflow.ai</database>
	</source>
	<size>
		<width>416</width>
		<height>416</height>
		<depth>3</depth>
	</size>
	<segmented>0</segmented>
	<object>
		<name>head</name>
		<pose>Unspecified</pose>
		<truncated>0</truncated>
		<difficult>0</difficult>
		<occluded>0</occluded>
		<bndbox>
			<xmin>60</xmin>
			<xmax>93</xmax>
			<ymin>140</ymin>
			<ymax>176</ymax>
		</bndbox>
	</object>
	<object>
		<name>head</name>
		<pose>Unspecified</pose>
		<truncated>0</truncated>
		<difficult>0</difficult>
		<occluded>0</occluded>
		<bndbox>
			<xmin>25</xmin>
			<xmax>46</xmax>
			<ymin>156</ymin>
			<ymax>185</ymax>
		</bndbox>
	</object>
	<object>
		<name>head</name>
		<pose>Unspecified</pose>
		<truncated>0</truncated>
		<difficult>0</difficult>
		<occluded>0</occluded>
		<bndbox>
			<xmin>133</xmin>
			<xmax>158</xmax>
			<ymin>151</ymin>
			<ymax>177</ymax>
		</bndbox>
	</object>
</annotation>
