<annotation>
	<folder></folder>
	<filename>004198_jpg.rf.29778d2b3e6d85abb9ffefbc4ee403f8.jpg</filename>
	<path>004198_jpg.rf.29778d2b3e6d85abb9ffefbc4ee403f8.jpg</path>
	<source>
		<database>roboflow.ai</database>
	</source>
	<size>
		<width>416</width>
		<height>416</height>
		<depth>3</depth>
	</size>
	<segmented>0</segmented>
	<object>
		<name>helmet</name>
		<pose>Unspecified</pose>
		<truncated>0</truncated>
		<difficult>0</difficult>
		<occluded>0</occluded>
		<bndbox>
			<xmin>150</xmin>
			<xmax>248</xmax>
			<ymin>119</ymin>
			<ymax>225</ymax>
		</bndbox>
	</object>
</annotation>
