<annotation>
	<folder></folder>
	<filename>004541_jpg.rf.be520d44465b1a1260da422d0475125d.jpg</filename>
	<path>004541_jpg.rf.be520d44465b1a1260da422d0475125d.jpg</path>
	<source>
		<database>roboflow.ai</database>
	</source>
	<size>
		<width>416</width>
		<height>416</height>
		<depth>3</depth>
	</size>
	<segmented>0</segmented>
	<object>
		<name>helmet</name>
		<pose>Unspecified</pose>
		<truncated>0</truncated>
		<difficult>0</difficult>
		<occluded>0</occluded>
		<bndbox>
			<xmin>105</xmin>
			<xmax>185</xmax>
			<ymin>81</ymin>
			<ymax>184</ymax>
		</bndbox>
	</object>
	<object>
		<name>helmet</name>
		<pose>Unspecified</pose>
		<truncated>0</truncated>
		<difficult>0</difficult>
		<occluded>0</occluded>
		<bndbox>
			<xmin>105</xmin>
			<xmax>186</xmax>
			<ymin>0</ymin>
			<ymax>42</ymax>
		</bndbox>
	</object>
</annotation>
